django_tenants_q/__init__.py
django_tenants_q/cluster.py
django_tenants_q/custom.py
django_tenants_q/utils.py
django_tenants_q/management/__init.py
django_tenants_q/management/commands/__init__.py
django_tenants_q/management/commands/mscluster.py
django_tenants_q-1.0.0.dist-info/LICENSE
django_tenants_q-1.0.0.dist-info/METADATA
django_tenants_q-1.0.0.dist-info/WHEEL
django_tenants_q-1.0.0.dist-info/top_level.txt
django_tenants_q-1.0.0.dist-info/RECORD
