Metadata-Version: 2.1
Name: django-tenants-q
Version: 1.0.0
Summary: An integration package for Django-Q with Django Tenants
Home-page: https://github.com/chaitanyadevle/django-tenants-q
Author: Chaitanya Devale
Author-email: chaitanyadevale11@gmail.com
License: MIT
Platform: UNKNOWN
Classifier: Programming Language :: Python :: 3
Classifier: License :: OSI Approved :: MIT License
Classifier: Operating System :: OS Independent
Requires-Python: >=3.7
License-File: LICENSE
Requires-Dist: django-tenants (>=3.3.2)
Requires-Dist: django-q (>=1.3.9)
Requires-Dist: croniter (>=1.0.15)
